{
  "flow_summary": "Establish stakes, teach workflow, introduce AI affordances, then complicate with legal/ethical layers and close with synthesis.",
  "acts_or_phases": [
    {
      "label": "Framing",
      "goal": "Motivate why screenplays and AI together matter now",
      "slide_range_hint": "1-5"
    },
    {
      "label": "Tools in practice",
      "goal": "Show how models assist ideation and drafting",
      "slide_range_hint": "6-11"
    },
    {
      "label": "Implications",
      "goal": "Copyright, guild context, authenticity",
      "slide_range_hint": "12-16"
    },
    {
      "label": "Synthesis",
      "goal": "Discussion and takeaways",
      "slide_range_hint": "17-18"
    }
  ],
  "progression_notes": "Each block adds a layer: craft, then capability, then consequence.",
  "rhetorical_strategy": "Instructor narrative with pauses for discussion on later slides",
  "transitions": [
    "From craft basics to tooling…",
    "Once we see what the tools do, we should ask who gets credit…",
    "Bringing it back to what you will try in class…"
  ]
}
